mcare/__init__.py
mcare-0.0.0.dist-info/METADATA
mcare-0.0.0.dist-info/WHEEL
mcare-0.0.0.dist-info/top_level.txt
mcare-0.0.0.dist-info/RECORD
