Metadata-Version: 2.4
Name: mcare
Version: 0.0.0
Summary: Implementation coming soon.
Author: Kinson Vernet
License-Expression: MIT
Requires-Python: >=3.10
